sitecustomize.py
zmfh_autoboot.pth
zmfh/__init__.py
zmfh/__main__.py
zmfh/_autoboot.py
zmfh/_constants.py
zmfh/_version.py
zmfh/cli_config.py
zmfh/config.py
zmfh/cli/__init__.py
zmfh/cli/doctor.py
zmfh/cli/main.py
zmfh/cli/policy_cmd.py
zmfh/cli/selftest_cmd.py
zmfh/cli/status_cmd.py
zmfh/cli/trace_cmd.py
zmfh/contracts/__init__.py
zmfh/contracts/api.py
zmfh/contracts/messages.py
zmfh/contracts/safety.py
zmfh/diagnostics/__init__.py
zmfh/diagnostics/checks.py
zmfh/diagnostics/doctor.py
zmfh/diagnostics/report.py
zmfh/evidence/__init__.py
zmfh/evidence/events.py
zmfh/evidence/formats.py
zmfh/evidence/log.py
zmfh/evidence/redact.py
zmfh/evidence/sink.py
zmfh/evidence/trace.py
zmfh/hook/__init__.py
zmfh/hook/chain.py
zmfh/hook/finder.py
zmfh/hook/guards.py
zmfh/hook/install.py
zmfh/hook/loader.py
zmfh/hook/meta_path.py
zmfh/policy/__init__.py
zmfh/policy/decision.py
zmfh/policy/defaults.py
zmfh/policy/load.py
zmfh/policy/model.py
zmfh/policy/rules.py
zmfh/policy/validate.py
zmfh/registry/__init__.py
zmfh/registry/cache.py
zmfh/registry/fingerprint.py
zmfh/registry/formats.py
zmfh/registry/index.py
zmfh/registry/scan.py
zmfh/registry/sources.py
zmfh/resolver/__init__.py
zmfh/resolver/fallback.py
zmfh/resolver/keyspace.py
zmfh/resolver/resolve.py
zmfh/resolver/spec_factory.py
zmfh/resolver/verify.py
zmfh/runtime/__init__.py
zmfh/runtime/bootstrap.py
zmfh/runtime/compat.py
zmfh/runtime/env.py
zmfh/runtime/failopen.py
zmfh/runtime/managed.py
zmfh/runtime/modes.py
zmfh/runtime/origins.py
zmfh/runtime/state.py
zmfh/util/__init__.py
zmfh/util/errors.py
zmfh/util/fs.py
zmfh/util/hashing.py
zmfh/util/jsonx.py
zmfh/util/platform.py
zmfh/util/safe.py
zmfh/util/time.py
zmfh-1.0.0.post1.dist-info/licenses/LICENSE
zmfh-1.0.0.post1.dist-info/licenses/NOTICE
zmfh-1.0.0.post1.dist-info/METADATA
zmfh-1.0.0.post1.dist-info/WHEEL
zmfh-1.0.0.post1.dist-info/top_level.txt
zmfh-1.0.0.post1.dist-info/RECORD
