Metadata-Version: 2.4
Name: zmfh
Version: 1.0.0.post1
Summary: ZMFH: Python import governance layer (fail-open by default).
Author: ZMFH contributors
License: MIT License
Project-URL: Homepage, https://pypi.org/project/zmfh/
Keywords: import,governance,resolver,policy,bootstrap,meta_path
Requires-Python: >=3.9
License-File: LICENSE
License-File: NOTICE
Dynamic: license-file
